element_zstack/__init__.py
element_zstack/bossdb.py
element_zstack/version.py
element_zstack/volume.py
element_zstack/export/__init__.py
element_zstack/export/bossdb_interface.py
element_zstack-0.1.2.dist-info/LICENSE
element_zstack-0.1.2.dist-info/METADATA
element_zstack-0.1.2.dist-info/WHEEL
element_zstack-0.1.2.dist-info/top_level.txt
element_zstack-0.1.2.dist-info/RECORD
