Metadata-Version: 2.1
Name: element-zstack
Version: 0.1.2
Summary: DataJoint Element for Volume Segmentation
Home-page: https://github.com/datajoint/element-zstack
Author: DataJoint
Author-email: info@datajoint.com
License: MIT
Keywords: neuroscience volume segmentation
Platform: UNKNOWN
License-File: LICENSE
Requires-Dist: datajoint >=0.13.0
Requires-Dist: element-interface >=0.3.0
Requires-Dist: intern >=1.4.1
Requires-Dist: tifffile >=2023.3.21
Requires-Dist: cellpose >=2.2
